nnweaver/__init__.py
nnweaver/activations.py
nnweaver/callbacks.py
nnweaver/losses.py
nnweaver/nn.py
nnweaver/optimizers.py
nnweaver/regularizers.py
nnweaver/utils.py
nnweaver/validation.py
nnweaver-0.2.dist-info/METADATA
nnweaver-0.2.dist-info/RECORD
nnweaver-0.2.dist-info/WHEEL
nnweaver-0.2.dist-info/top_level.txt
